{"title":"Realidade Aumentada – Hipsters #117","releaseDate":"09/10/2018","tags":["Podcast","programação"],"people":["Paulo Silveira","Charles Barros","Pedro Almeida","André Breves"],"disqusUrl":"https://disqus.com/embed/comments/?base=default&f=hipsterspontotech&t_i=1940%20https%3A%2F%2Fhipsters.tech%2F%3Fp%3D1940&t_u=https%3A%2F%2Fhipsters.tech%2Frealidade-aumentada-hipsters-117%2F&t_e=Realidade%20Aumentada%20%E2%80%93%20Hipsters%20%23117&t_d=Realidade%20Aumentada%20-%20Hipsters%20%23117%20-%20Hipsters%20Ponto%20TechHipsters%20Ponto%20Tech&t_t=Realidade%20Aumentada%20%E2%80%93%20Hipsters%20%23117&s_o=default#version=600a9bd88a8393b10140eb70dcc30fd1","comments":[{"author":"VINICIUS S SOUZA","comment":"Ótimo conteúdo, como sempre. Parabéns, pessoal.Tenho uma sugestão de tema. A famigerada urna eletrônica, sua segurança, arquitetura... Seria um ótimo tema"},{"author":"Rômulo Innocêncio","comment":"E tinha que conseguir o código para analizar numa live kkkkkkk"}]}